waqi-python/client.py
waqi-python/helpers.py
waqi-python/objects.py
waqi_python/client.py
waqi_python/exceptions.py
waqi_python/helpers.py
waqi_python/objects.py
waqi_python-0.2.2.dist-info/LICENSE
waqi_python-0.2.2.dist-info/METADATA
waqi_python-0.2.2.dist-info/WHEEL
waqi_python-0.2.2.dist-info/top_level.txt
waqi_python-0.2.2.dist-info/RECORD
