Metadata-Version: 2.1
Name: waqi-python
Version: 0.2.2
Summary: Python wrapper for the World Air Quality Index Project JSON API
Home-page: https://github.com/danoscarmike/waqi-python
Author: Dan O'Meara
Author-email: omeara.dan@gmail.com
License: UNKNOWN
Platform: UNKNOWN
Classifier: Programming Language :: Python :: 3
Classifier: Development Status :: 1 - Planning
Classifier: License :: OSI Approved :: MIT License
Requires-Dist: python-dateutil
Requires-Dist: requests
